CHANGES.txt
DEPENDENCIES.txt
README.txt
bootstrap.py
buildout.cfg
setup.py
src/ks/__init__.py
src/ks.zcml.smartmenuitem.egg-info/PKG-INFO
src/ks.zcml.smartmenuitem.egg-info/SOURCES.txt
src/ks.zcml.smartmenuitem.egg-info/dependency_links.txt
src/ks.zcml.smartmenuitem.egg-info/namespace_packages.txt
src/ks.zcml.smartmenuitem.egg-info/not-zip-safe
src/ks.zcml.smartmenuitem.egg-info/requires.txt
src/ks.zcml.smartmenuitem.egg-info/top_level.txt
src/ks/zcml/__init__.py
src/ks/zcml/smartmenuitem/README.txt
src/ks/zcml/smartmenuitem/__init__.py
src/ks/zcml/smartmenuitem/configure.zcml
src/ks/zcml/smartmenuitem/meta.zcml
src/ks/zcml/smartmenuitem/metaconfigure.py
src/ks/zcml/smartmenuitem/metadirectives.py
src/ks/zcml/smartmenuitem/demo/__init__.py
src/ks/zcml/smartmenuitem/demo/configure.zcml
src/ks/zcml/smartmenuitem/demo/etc/ks.zcml.smartmenuitem.demo-configure.zcml
src/ks/zcml/smartmenuitem/etc/ks.zcml.smartmenuitem-configure.zcml