Metadata-Version: 1.0
Name: ks.zcml.smartmenuitem
Version: 1.0.1
Summary: Create really "smart" menu items with ks.zcml.smartmenuitem for Hivurt
Home-page: http://code.keysolutionscorp.com/downloads/public/pypi/ks.zcml.smartmenuitem
Author: Key Solutions Development TEAM
Author-email: ksd-team@keysolutions.ru
License: ZPL 2.1
Platform: UNKNOWN
Classifier: Intended Audience :: Developers
Classifier: License :: OSI Approved :: Zope Public License
Classifier: Programming Language :: Python
Classifier: Natural Language :: English
Classifier: Operating System :: OS Independent
Classifier: Topic :: Internet :: WWW/HTTP
Classifier: Topic :: Software Development
Classifier: Framework :: Zope3
